{
   "runs" : [
      {
         "OS" : "linux",
         "abstract" : "Read-only Database Abstraction Layer (ORM)",
         "dir" : "/home/runner/work/Database-Abstraction/Database-Abstraction",
         "finish" : 1758025842.70311,
         "name" : "Database-Abstraction",
         "perl" : "5.40.3",
         "run" : "-e",
         "start" : 1758025842.70283,
         "version" : "0.32"
      },
      {
         "OS" : "linux",
         "abstract" : "Read-only Database Abstraction Layer (ORM)",
         "dir" : "/home/runner/work/Database-Abstraction/Database-Abstraction",
         "finish" : 1758025842.86995,
         "name" : "Database-Abstraction",
         "perl" : "5.40.3",
         "run" : "-e",
         "start" : 1758025842.86973,
         "version" : "0.32"
      },
      {
         "OS" : "linux",
         "abstract" : "Read-only Database Abstraction Layer (ORM)",
         "dir" : "/home/runner/work/Database-Abstraction/Database-Abstraction",
         "finish" : 1758025843.03432,
         "name" : "Database-Abstraction",
         "perl" : "5.40.3",
         "run" : "-e",
         "start" : 1758025843.034,
         "version" : "0.32"
      },
      {
         "OS" : "linux",
         "abstract" : "Read-only Database Abstraction Layer (ORM)",
         "dir" : "/home/runner/work/Database-Abstraction/Database-Abstraction",
         "finish" : 1758025843.20283,
         "name" : "Database-Abstraction",
         "perl" : "5.40.3",
         "run" : "-e",
         "start" : 1758025843.20252,
         "version" : "0.32"
      },
      {
         "OS" : "linux",
         "abstract" : "Read-only Database Abstraction Layer (ORM)",
         "dir" : "/home/runner/work/Database-Abstraction/Database-Abstraction",
         "finish" : 1758025843.36918,
         "name" : "Database-Abstraction",
         "perl" : "5.40.3",
         "run" : "-e",
         "start" : 1758025843.36896,
         "version" : "0.32"
      },
      {
         "OS" : "linux",
         "abstract" : "Read-only Database Abstraction Layer (ORM)",
         "dir" : "/home/runner/work/Database-Abstraction/Database-Abstraction",
         "finish" : 1758025843.535,
         "name" : "Database-Abstraction",
         "perl" : "5.40.3",
         "run" : "-e",
         "start" : 1758025843.53477,
         "version" : "0.32"
      },
      {
         "OS" : "linux",
         "abstract" : "Read-only Database Abstraction Layer (ORM)",
         "dir" : "/home/runner/work/Database-Abstraction/Database-Abstraction",
         "finish" : 1758025843.70631,
         "name" : "Database-Abstraction",
         "perl" : "5.40.3",
         "run" : "-e",
         "start" : 1758025843.70609,
         "version" : "0.32"
      },
      {
         "OS" : "linux",
         "abstract" : "Read-only Database Abstraction Layer (ORM)",
         "dir" : "/home/runner/work/Database-Abstraction/Database-Abstraction",
         "finish" : 1758025843.87411,
         "name" : "Database-Abstraction",
         "perl" : "5.40.3",
         "run" : "-e",
         "start" : 1758025843.87389,
         "version" : "0.32"
      },
      {
         "OS" : "linux",
         "abstract" : "Read-only Database Abstraction Layer (ORM)",
         "dir" : "/home/runner/work/Database-Abstraction/Database-Abstraction",
         "finish" : 1758025844.0566,
         "name" : "Database-Abstraction",
         "perl" : "5.40.3",
         "run" : "-e",
         "start" : 1758025844.04448,
         "version" : "0.32"
      },
      {
         "OS" : "linux",
         "abstract" : "Read-only Database Abstraction Layer (ORM)",
         "dir" : "/home/runner/work/Database-Abstraction/Database-Abstraction",
         "finish" : 1758025858.83278,
         "name" : "Database-Abstraction",
         "perl" : "5.40.3",
         "run" : "-e",
         "start" : 1758025844.25548,
         "version" : "0.32"
      },
      {
         "OS" : "linux",
         "abstract" : "Read-only Database Abstraction Layer (ORM)",
         "dir" : "/home/runner/work/Database-Abstraction/Database-Abstraction",
         "finish" : 1758025844.40063,
         "name" : "Database-Abstraction",
         "perl" : "5.40.3",
         "run" : "-e",
         "start" : 1758025844.40047,
         "version" : "0.32"
      },
      {
         "OS" : "linux",
         "abstract" : "Read-only Database Abstraction Layer (ORM)",
         "dir" : "/home/runner/work/Database-Abstraction/Database-Abstraction",
         "finish" : 1758025844.74333,
         "name" : "Database-Abstraction",
         "perl" : "5.40.3",
         "run" : "t/00-load.t",
         "start" : 1758025844.74206,
         "version" : "0.32"
      },
      {
         "OS" : "linux",
         "abstract" : "Read-only Database Abstraction Layer (ORM)",
         "dir" : "/home/runner/work/Database-Abstraction/Database-Abstraction",
         "finish" : 1758025845.42138,
         "name" : "Database-Abstraction",
         "perl" : "5.40.3",
         "run" : "t/10-compile.t",
         "start" : 1758025845.19375,
         "version" : "0.32"
      },
      {
         "OS" : "linux",
         "abstract" : "Read-only Database Abstraction Layer (ORM)",
         "dir" : "/home/runner/work/Database-Abstraction/Database-Abstraction",
         "finish" : 1758025845.76032,
         "name" : "Database-Abstraction",
         "perl" : "5.40.3",
         "run" : "t/20-new.t",
         "start" : 1758025845.67294,
         "version" : "0.32"
      },
      {
         "OS" : "linux",
         "abstract" : "Read-only Database Abstraction Layer (ORM)",
         "dir" : "/home/runner/work/Database-Abstraction/Database-Abstraction",
         "finish" : 1758025846.34279,
         "name" : "Database-Abstraction",
         "perl" : "5.40.3",
         "run" : "t/30-basics.t",
         "start" : 1758025846.24675,
         "version" : "0.32"
      },
      {
         "OS" : "linux",
         "abstract" : "Read-only Database Abstraction Layer (ORM)",
         "dir" : "/home/runner/work/Database-Abstraction/Database-Abstraction",
         "finish" : 1758025846.97058,
         "name" : "Database-Abstraction",
         "perl" : "5.40.3",
         "run" : "t/carp.t",
         "start" : 1758025846.82266,
         "version" : "0.32"
      },
      {
         "OS" : "linux",
         "abstract" : "Read-only Database Abstraction Layer (ORM)",
         "dir" : "/home/runner/work/Database-Abstraction/Database-Abstraction",
         "finish" : 1758025847.46477,
         "name" : "Database-Abstraction",
         "perl" : "5.40.3",
         "run" : "t/chi.t",
         "start" : 1758025847.46434,
         "version" : "0.32"
      },
      {
         "OS" : "linux",
         "abstract" : "Read-only Database Abstraction Layer (ORM)",
         "dir" : "/home/runner/work/Database-Abstraction/Database-Abstraction",
         "finish" : 1758025847.70577,
         "name" : "Database-Abstraction",
         "perl" : "5.40.3",
         "run" : "t/comment-spelling.t",
         "start" : 1758025847.70555,
         "version" : "0.32"
      },
      {
         "OS" : "linux",
         "abstract" : "Read-only Database Abstraction Layer (ORM)",
         "dir" : "/home/runner/work/Database-Abstraction/Database-Abstraction",
         "finish" : 1758025848.12434,
         "name" : "Database-Abstraction",
         "perl" : "5.40.3",
         "run" : "t/csv.t",
         "start" : 1758025847.96398,
         "version" : "0.32"
      },
      {
         "OS" : "linux",
         "abstract" : "Read-only Database Abstraction Layer (ORM)",
         "dir" : "/home/runner/work/Database-Abstraction/Database-Abstraction",
         "finish" : 1758025848.7752,
         "name" : "Database-Abstraction",
         "perl" : "5.40.3",
         "run" : "t/csv_id.t",
         "start" : 1758025848.62118,
         "version" : "0.32"
      },
      {
         "OS" : "linux",
         "abstract" : "Read-only Database Abstraction Layer (ORM)",
         "dir" : "/home/runner/work/Database-Abstraction/Database-Abstraction",
         "finish" : 1758025849.2735,
         "name" : "Database-Abstraction",
         "perl" : "5.40.3",
         "run" : "t/db.t",
         "start" : 1758025849.27324,
         "version" : "0.32"
      },
      {
         "OS" : "linux",
         "abstract" : "Read-only Database Abstraction Layer (ORM)",
         "dir" : "/home/runner/work/Database-Abstraction/Database-Abstraction",
         "finish" : 1758025849.55202,
         "name" : "Database-Abstraction",
         "perl" : "5.40.3",
         "run" : "t/db_noentry.t",
         "start" : 1758025849.55174,
         "version" : "0.32"
      },
      {
         "OS" : "linux",
         "abstract" : "Read-only Database Abstraction Layer (ORM)",
         "dir" : "/home/runner/work/Database-Abstraction/Database-Abstraction",
         "finish" : 1758025849.79464,
         "name" : "Database-Abstraction",
         "perl" : "5.40.3",
         "run" : "t/eof.t",
         "start" : 1758025849.79439,
         "version" : "0.32"
      },
      {
         "OS" : "linux",
         "abstract" : "Read-only Database Abstraction Layer (ORM)",
         "dir" : "/home/runner/work/Database-Abstraction/Database-Abstraction",
         "finish" : 1758025850.02889,
         "name" : "Database-Abstraction",
         "perl" : "5.40.3",
         "run" : "t/eol.t",
         "start" : 1758025850.02865,
         "version" : "0.32"
      },
      {
         "OS" : "linux",
         "abstract" : "Read-only Database Abstraction Layer (ORM)",
         "dir" : "/home/runner/work/Database-Abstraction/Database-Abstraction",
         "finish" : 1758025850.36513,
         "name" : "Database-Abstraction",
         "perl" : "5.40.3",
         "run" : "t/init.t",
         "start" : 1758025850.28742,
         "version" : "0.32"
      },
      {
         "OS" : "linux",
         "abstract" : "Read-only Database Abstraction Layer (ORM)",
         "dir" : "/home/runner/work/Database-Abstraction/Database-Abstraction",
         "finish" : 1758025851.02524,
         "name" : "Database-Abstraction",
         "perl" : "5.40.3",
         "run" : "t/logger.t",
         "start" : 1758025850.84792,
         "version" : "0.32"
      },
      {
         "OS" : "linux",
         "abstract" : "Read-only Database Abstraction Layer (ORM)",
         "dir" : "/home/runner/work/Database-Abstraction/Database-Abstraction",
         "finish" : 1758025851.67584,
         "name" : "Database-Abstraction",
         "perl" : "5.40.3",
         "run" : "t/no_entry.t",
         "start" : 1758025851.52418,
         "version" : "0.32"
      },
      {
         "OS" : "linux",
         "abstract" : "Read-only Database Abstraction Layer (ORM)",
         "dir" : "/home/runner/work/Database-Abstraction/Database-Abstraction",
         "finish" : 1758025852.31327,
         "name" : "Database-Abstraction",
         "perl" : "5.40.3",
         "run" : "t/passwd.t",
         "start" : 1758025852.16424,
         "version" : "0.32"
      },
      {
         "OS" : "linux",
         "abstract" : "Read-only Database Abstraction Layer (ORM)",
         "dir" : "/home/runner/work/Database-Abstraction/Database-Abstraction",
         "finish" : 1758025852.77769,
         "name" : "Database-Abstraction",
         "perl" : "5.40.3",
         "run" : "t/pod-cm.t",
         "start" : 1758025852.77739,
         "version" : "0.32"
      },
      {
         "OS" : "linux",
         "abstract" : "Read-only Database Abstraction Layer (ORM)",
         "dir" : "/home/runner/work/Database-Abstraction/Database-Abstraction",
         "finish" : 1758025853.01437,
         "name" : "Database-Abstraction",
         "perl" : "5.40.3",
         "run" : "t/pod-coverage.t",
         "start" : 1758025853.0141,
         "version" : "0.32"
      },
      {
         "OS" : "linux",
         "abstract" : "Read-only Database Abstraction Layer (ORM)",
         "dir" : "/home/runner/work/Database-Abstraction/Database-Abstraction",
         "finish" : 1758025853.25111,
         "name" : "Database-Abstraction",
         "perl" : "5.40.3",
         "run" : "t/pod-links.t",
         "start" : 1758025853.25087,
         "version" : "0.32"
      },
      {
         "OS" : "linux",
         "abstract" : "Read-only Database Abstraction Layer (ORM)",
         "dir" : "/home/runner/work/Database-Abstraction/Database-Abstraction",
         "finish" : 1758025853.4867,
         "name" : "Database-Abstraction",
         "perl" : "5.40.3",
         "run" : "t/pod-snippets.t",
         "start" : 1758025853.48644,
         "version" : "0.32"
      },
      {
         "OS" : "linux",
         "abstract" : "Read-only Database Abstraction Layer (ORM)",
         "dir" : "/home/runner/work/Database-Abstraction/Database-Abstraction",
         "finish" : 1758025853.72115,
         "name" : "Database-Abstraction",
         "perl" : "5.40.3",
         "run" : "t/pod-spelling.t",
         "start" : 1758025853.72093,
         "version" : "0.32"
      },
      {
         "OS" : "linux",
         "abstract" : "Read-only Database Abstraction Layer (ORM)",
         "dir" : "/home/runner/work/Database-Abstraction/Database-Abstraction",
         "finish" : 1758025853.95622,
         "name" : "Database-Abstraction",
         "perl" : "5.40.3",
         "run" : "t/pod-synopsis.t",
         "start" : 1758025853.95597,
         "version" : "0.32"
      },
      {
         "OS" : "linux",
         "abstract" : "Read-only Database Abstraction Layer (ORM)",
         "dir" : "/home/runner/work/Database-Abstraction/Database-Abstraction",
         "finish" : 1758025854.19092,
         "name" : "Database-Abstraction",
         "perl" : "5.40.3",
         "run" : "t/pod.t",
         "start" : 1758025854.19065,
         "version" : "0.32"
      },
      {
         "OS" : "linux",
         "abstract" : "Read-only Database Abstraction Layer (ORM)",
         "dir" : "/home/runner/work/Database-Abstraction/Database-Abstraction",
         "finish" : 1758025854.60047,
         "name" : "Database-Abstraction",
         "perl" : "5.40.3",
         "run" : "t/psv.t",
         "start" : 1758025854.4526,
         "version" : "0.32"
      },
      {
         "OS" : "linux",
         "abstract" : "Read-only Database Abstraction Layer (ORM)",
         "dir" : "/home/runner/work/Database-Abstraction/Database-Abstraction",
         "finish" : 1758025855.07321,
         "name" : "Database-Abstraction",
         "perl" : "5.40.3",
         "run" : "t/tabs.t",
         "start" : 1758025855.07292,
         "version" : "0.32"
      },
      {
         "OS" : "linux",
         "abstract" : "Read-only Database Abstraction Layer (ORM)",
         "dir" : "/home/runner/work/Database-Abstraction/Database-Abstraction",
         "finish" : 1758025855.50087,
         "name" : "Database-Abstraction",
         "perl" : "5.40.3",
         "run" : "t/test7.t",
         "start" : 1758025855.33786,
         "version" : "0.32"
      },
      {
         "OS" : "linux",
         "abstract" : "Read-only Database Abstraction Layer (ORM)",
         "dir" : "/home/runner/work/Database-Abstraction/Database-Abstraction",
         "finish" : 1758025856.14566,
         "name" : "Database-Abstraction",
         "perl" : "5.40.3",
         "run" : "t/test8.t",
         "start" : 1758025855.99449,
         "version" : "0.32"
      },
      {
         "OS" : "linux",
         "abstract" : "Read-only Database Abstraction Layer (ORM)",
         "dir" : "/home/runner/work/Database-Abstraction/Database-Abstraction",
         "finish" : 1758025856.79335,
         "name" : "Database-Abstraction",
         "perl" : "5.40.3",
         "run" : "t/two_databases.t",
         "start" : 1758025856.71877,
         "version" : "0.32"
      },
      {
         "OS" : "linux",
         "abstract" : "Read-only Database Abstraction Layer (ORM)",
         "dir" : "/home/runner/work/Database-Abstraction/Database-Abstraction",
         "finish" : 1758025857.26574,
         "name" : "Database-Abstraction",
         "perl" : "5.40.3",
         "run" : "t/vars.t",
         "start" : 1758025857.26543,
         "version" : "0.32"
      },
      {
         "OS" : "linux",
         "abstract" : "Read-only Database Abstraction Layer (ORM)",
         "dir" : "/home/runner/work/Database-Abstraction/Database-Abstraction",
         "finish" : 1758025857.5054,
         "name" : "Database-Abstraction",
         "perl" : "5.40.3",
         "run" : "t/version.t",
         "start" : 1758025857.50513,
         "version" : "0.32"
      },
      {
         "OS" : "linux",
         "abstract" : "Read-only Database Abstraction Layer (ORM)",
         "dir" : "/home/runner/work/Database-Abstraction/Database-Abstraction",
         "finish" : 1758025857.97997,
         "name" : "Database-Abstraction",
         "perl" : "5.40.3",
         "run" : "t/xml.t",
         "start" : 1758025857.86105,
         "version" : "0.32"
      },
      {
         "OS" : "linux",
         "abstract" : "Read-only Database Abstraction Layer (ORM)",
         "dir" : "/home/runner/work/Database-Abstraction/Database-Abstraction",
         "finish" : 1758025858.57879,
         "name" : "Database-Abstraction",
         "perl" : "5.40.3",
         "run" : "t/xml_record.t",
         "start" : 1758025858.47596,
         "version" : "0.32"
      }
   ],
   "summary" : {
      "Total" : {
         "branch" : {
            "covered" : 218,
            "error" : 178,
            "percentage" : 55.0505050505051,
            "total" : 396,
            "uncoverable" : 0
         },
         "condition" : {
            "covered" : 87,
            "error" : 95,
            "percentage" : 47.8021978021978,
            "total" : 182,
            "uncoverable" : 0
         },
         "statement" : {
            "covered" : 512,
            "error" : 208,
            "percentage" : 71.1111111111111,
            "total" : 720
         },
         "subroutine" : {
            "covered" : 37,
            "error" : 3,
            "percentage" : 92.5,
            "total" : 40
         },
         "total" : {
            "covered" : 854,
            "error" : 484,
            "percentage" : 63.8266068759342,
            "total" : 1338,
            "uncoverable" : 0
         }
      },
      "blib/lib/Database/Abstraction.pm" : {
         "branch" : {
            "covered" : 218,
            "error" : 178,
            "percentage" : 55.0505050505051,
            "total" : 396,
            "uncoverable" : 0
         },
         "condition" : {
            "covered" : 87,
            "error" : 95,
            "percentage" : 47.8021978021978,
            "total" : 182,
            "uncoverable" : 0
         },
         "statement" : {
            "covered" : 512,
            "error" : 208,
            "percentage" : 71.1111111111111,
            "total" : 720
         },
         "subroutine" : {
            "covered" : 37,
            "error" : 3,
            "percentage" : 92.5,
            "total" : 40
         },
         "total" : {
            "covered" : 854,
            "error" : 484,
            "percentage" : 63.8266068759342,
            "total" : 1338,
            "uncoverable" : 0
         }
      }
   }
}
